nmaipy/__init__.py
nmaipy/__version__.py
nmaipy/aoi_io.py
nmaipy/api_common.py
nmaipy/base_exporter.py
nmaipy/cgroup_memory.py
nmaipy/constants.py
nmaipy/coverage_utils.py
nmaipy/exporter.py
nmaipy/feature_api.py
nmaipy/feature_attributes.py
nmaipy/geometry_utils.py
nmaipy/log.py
nmaipy/parcels.py
nmaipy/primary_feature_selection.py
nmaipy/reference_code.py
nmaipy/roof_age_api.py
nmaipy/roof_age_exporter.py
nmaipy-4.0.3.dist-info/licenses/LICENSE
nmaipy-4.0.3.dist-info/METADATA
nmaipy-4.0.3.dist-info/WHEEL
nmaipy-4.0.3.dist-info/top_level.txt
nmaipy-4.0.3.dist-info/RECORD
