Metadata-Version: 2.4
Name: nmaipy
Version: 4.0.3
Summary: Nearmap AI Python Library for extracting AI features from aerial imagery
Author-email: Nearmap AI Systems <ai.systems@nearmap.com>
Maintainer-email: Nearmap AI Systems <ai.systems@nearmap.com>
License:                                  Apache License
Project-URL: Homepage, https://github.com/nearmap/nmaipy
Project-URL: Documentation, https://github.com/nearmap/nmaipy#readme
Project-URL: Repository, https://github.com/nearmap/nmaipy.git
Project-URL: Bug Tracker, https://github.com/nearmap/nmaipy/issues
Keywords: nearmap,ai,geospatial,gis,aerial,imagery,buildings,vegetation
Classifier: Development Status :: 4 - Beta
Classifier: Intended Audience :: Developers
Classifier: Intended Audience :: Science/Research
Classifier: License :: OSI Approved :: Apache Software License
Classifier: Operating System :: OS Independent
Classifier: Programming Language :: Python :: 3
Classifier: Programming Language :: Python :: 3.12
Classifier: Topic :: Scientific/Engineering :: GIS
Classifier: Topic :: Scientific/Engineering :: Artificial Intelligence
Requires-Python: >=3.12
License-File: LICENSE
Requires-Dist: fsspec
Requires-Dist: geopandas>=1.1.0
Requires-Dist: numpy
Requires-Dist: pandas
Requires-Dist: psutil
Requires-Dist: pyarrow
Requires-Dist: pyproj
Requires-Dist: python-dotenv
Requires-Dist: requests
Requires-Dist: rtree
Requires-Dist: s3fs
Requires-Dist: shapely
Requires-Dist: stringcase
Requires-Dist: tqdm
Provides-Extra: dev
Requires-Dist: black; extra == "dev"
Requires-Dist: isort; extra == "dev"
Requires-Dist: pytest; extra == "dev"
Requires-Dist: build; extra == "dev"
Requires-Dist: twine; extra == "dev"
Provides-Extra: notebooks
Requires-Dist: ipykernel; extra == "notebooks"
Requires-Dist: matplotlib; extra == "notebooks"
Dynamic: license-file
